CHANGES.rst
MANIFEST.in
README.rst
setup.py
collective/__init__.py
collective.pdftransform.egg-info/PKG-INFO
collective.pdftransform.egg-info/SOURCES.txt
collective.pdftransform.egg-info/dependency_links.txt
collective.pdftransform.egg-info/entry_points.txt
collective.pdftransform.egg-info/namespace_packages.txt
collective.pdftransform.egg-info/not-zip-safe
collective.pdftransform.egg-info/requires.txt
collective.pdftransform.egg-info/top_level.txt
collective/pdftransform/__init__.py
collective/pdftransform/configure.zcml
collective/pdftransform/messagefactory.py
collective/pdftransform/patch.py
collective/pdftransform/pdf_image.py
collective/pdftransform/rebuild_i18n.sh
collective/pdftransform/utils.py
collective/pdftransform/validator.py
collective/pdftransform/version.txt
collective/pdftransform/Extensions/Install.py
collective/pdftransform/Extensions/__init__.py
collective/pdftransform/locales/collective.pdftransform.pot
collective/pdftransform/locales/en/LC_MESSAGES/collective.pdftransform.mo
collective/pdftransform/locales/en/LC_MESSAGES/collective.pdftransform.po
collective/pdftransform/locales/fr/LC_MESSAGES/collective.pdftransform.mo
collective/pdftransform/locales/fr/LC_MESSAGES/collective.pdftransform.po
collective/pdftransform/locales/nl/LC_MESSAGES/collective.pdftransform.mo
collective/pdftransform/locales/nl/LC_MESSAGES/collective.pdftransform.po
docs/INSTALL.txt
docs/LICENSE.GPL
docs/LICENSE.txt