Metadata-Version: 1.1
Name: collective.pdftransform
Version: 0.5
Summary: A set of portal transform to change pdf into images
Home-page: http://github.com/zestsoftware/collective.pdftransform
Author: Zest software
Author-email: info@zestsoftware.nl
License: GPL
Platform: UNKNOWN
Classifier: Framework :: Plone
Classifier: Programming Language :: Python
